astro_image_display_api/__init__.py
astro_image_display_api/_version.py
astro_image_display_api/api_test.py
astro_image_display_api/image_viewer_logic.py
astro_image_display_api/interface_definition.py
astro_image_display_api-0.2.0.dist-info/METADATA
astro_image_display_api-0.2.0.dist-info/WHEEL
astro_image_display_api-0.2.0.dist-info/licenses/LICENSE
astro_image_display_api-0.2.0.dist-info/RECORD
