Metadata-Version: 2.4
Name: astro-image-display-api
Version: 0.2.0
Summary: Astronomical image display API definition for cross-backend interoperability
Project-URL: Documentation, https://github.com/astropy/astro-image-display-api#readme
Project-URL: Issues, https://github.com/astropy/astro-image-display-api/issues
Project-URL: Source, https://github.com/astropy/astro-image-display-api
Author-email: Matt Craig <mattwcraig@gmail.com>
License-Expression: BSD-3-Clause
License-File: LICENSE
Classifier: Development Status :: 4 - Beta
Classifier: Programming Language :: Python
Classifier: Programming Language :: Python :: 3.12
Classifier: Programming Language :: Python :: 3.13
Classifier: Programming Language :: Python :: Implementation :: CPython
Requires-Python: >=3.12
Requires-Dist: astropy
Requires-Dist: numpy
Provides-Extra: docs
Requires-Dist: graphviz; extra == 'docs'
Requires-Dist: sphinx; extra == 'docs'
Requires-Dist: sphinx-astropy[confv2]; extra == 'docs'
Requires-Dist: sphinx-design; extra == 'docs'
Provides-Extra: test
Requires-Dist: black; extra == 'test'
Requires-Dist: pre-commit; extra == 'test'
Requires-Dist: pytest-astropy; extra == 'test'
Requires-Dist: ruff; extra == 'test'
Requires-Dist: tox; extra == 'test'
